[
 {
  "cible": "ault",
  "osm": "node/620897376",
  "nom": "Ault",
  "lat": 50.105,
  "lon": 1.4537,
  "car": null,
  "periode": "12",
  "portee": "18",
  "hauteur": null,
  "couleur": "white",
  "groupe": "3",
  "type": "landmark",
  "wikipedia": null
 },
 {
  "cible": "berck",
  "osm": "way/132169637",
  "nom": "Phare de Berck",
  "lat": 50.3983,
  "lon": 1.5608,
  "car": "Fl",
  "periode": "5",
  "portee": "23",
  "hauteur": "44",
  "couleur": "white",
  "groupe": null,
  "type": "landmark",
  "wikipedia": "fr:Phare de Berck"
 },
 {
  "cible": "carnot",
  "osm": "node/1431605242",
  "nom": "",
  "lat": 50.7274,
  "lon": 1.5777,
  "car": "Oc",
  "periode": "6",
  "portee": "6",
  "hauteur": "8",
  "couleur": "red",
  "groupe": "2",
  "type": "light_minor",
  "wikipedia": null
 },
 {
  "cible": "carnot",
  "osm": "node/1431605243",
  "nom": "",
  "lat": 50.7278,
  "lon": 1.575,
  "car": "Iso",
  "periode": "4",
  "portee": "5",
  "hauteur": "8",
  "couleur": "green",
  "groupe": null,
  "type": "light_minor",
  "wikipedia": null
 },
 {
  "cible": "carnot",
  "osm": "node/1431605303",
  "nom": "",
  "lat": 50.7316,
  "lon": 1.5853,
  "car": "F",
  "periode": null,
  "portee": "5",
  "hauteur": "17",
  "couleur": "green",
  "groupe": null,
  "type": "light_minor",
  "wikipedia": null
 },
 {
  "cible": "carnot",
  "osm": "node/1431605331",
  "nom": "Le Phare rouge",
  "lat": 50.7318,
  "lon": 1.5874,
  "car": "F",
  "periode": null,
  "portee": "7",
  "hauteur": "11",
  "couleur": "red",
  "groupe": null,
  "type": "light_minor",
  "wikipedia": null
 },
 {
  "cible": "carnot",
  "osm": "node/1543861975",
  "nom": "",
  "lat": 50.7226,
  "lon": 1.5648,
  "car": "F",
  "periode": null,
  "portee": "13",
  "hauteur": "23",
  "couleur": "red",
  "groupe": null,
  "type": "light_minor",
  "wikipedia": null
 },
 {
  "cible": "carnot",
  "osm": "node/1543861985",
  "nom": "",
  "lat": 50.7268,
  "lon": 1.5667,
  "car": "F",
  "periode": null,
  "portee": "8",
  "hauteur": "16",
  "couleur": "green",
  "groupe": null,
  "type": "light_minor",
  "wikipedia": null
 },
 {
  "cible": "carnot",
  "osm": "node/1543861991",
  "nom": "",
  "lat": 50.7451,
  "lon": 1.5697,
  "car": "Fl",
  "periode": "6",
  "portee": "7",
  "hauteur": "10",
  "couleur": "red",
  "groupe": "2",
  "type": "light_minor",
  "wikipedia": null
 },
 {
  "cible": "carnot",
  "osm": "node/3627205046",
  "nom": "",
  "lat": 50.7406,
  "lon": 1.5676,
  "car": "Fl",
  "periode": "15",
  "portee": "19",
  "hauteur": "25",
  "couleur": "white",
  "groupe": "2+1",
  "type": "light_major",
  "wikipedia": null
 },
 {
  "cible": "cayeux-controle",
  "osm": "node/623430641",
  "nom": "Cayeux-sur-Mer",
  "lat": 50.1943,
  "lon": 1.5121,
  "car": "Fl",
  "periode": "5",
  "portee": "22",
  "hauteur": "32",
  "couleur": "red",
  "groupe": null,
  "type": "landmark",
  "wikipedia": null
 },
 {
  "cible": "chausey",
  "osm": "node/1543876081",
  "nom": "",
  "lat": 48.8695,
  "lon": -1.8224,
  "car": "Fl",
  "periode": "5",
  "portee": "23",
  "hauteur": "39",
  "couleur": "white",
  "groupe": null,
  "type": "light_major",
  "wikipedia": null
 },
 {
  "cible": "chausey",
  "osm": "way/135525569",
  "nom": "Phare de Chausey",
  "lat": 48.8695,
  "lon": -1.8224,
  "car": null,
  "periode": null,
  "portee": null,
  "hauteur": "17",
  "couleur": null,
  "groupe": null,
  "type": null,
  "wikipedia": "fr:Phare de Chausey"
 },
 {
  "cible": "fort-ouest",
  "osm": "node/1543874557",
  "nom": "",
  "lat": 49.6591,
  "lon": -1.6409,
  "car": "Q",
  "periode": null,
  "portee": "10",
  "hauteur": "11",
  "couleur": "green",
  "groupe": null,
  "type": "light_minor",
  "wikipedia": null
 },
 {
  "cible": "fort-ouest",
  "osm": "node/1543874619",
  "nom": "",
  "lat": 49.6743,
  "lon": -1.6478,
  "car": "Fl",
  "periode": "15",
  "portee": "24",
  "hauteur": null,
  "couleur": "white",
  "groupe": "3",
  "type": "light_major",
  "wikipedia": null
 },
 {
  "cible": "fort-ouest",
  "osm": "node/1543874651",
  "nom": "",
  "lat": 49.6594,
  "lon": -1.6322,
  "car": "Q",
  "periode": null,
  "portee": "17",
  "hauteur": null,
  "couleur": "white",
  "groupe": null,
  "type": "light_major",
  "wikipedia": null
 },
 {
  "cible": "fort-ouest",
  "osm": "node/1543874658",
  "nom": "",
  "lat": 49.6591,
  "lon": -1.6329,
  "car": "Q",
  "periode": null,
  "portee": "19",
  "hauteur": "5",
  "couleur": "white",
  "groupe": null,
  "type": "light_major",
  "wikipedia": null
 },
 {
  "cible": "fort-ouest",
  "osm": "node/1543874664",
  "nom": "",
  "lat": 49.6717,
  "lon": -1.6633,
  "car": "Fl",
  "periode": "15",
  "portee": "4",
  "hauteur": "8",
  "couleur": "green",
  "groupe": "4",
  "type": "light_minor",
  "wikipedia": null
 },
 {
  "cible": "fort-ouest",
  "osm": "way/264908255",
  "nom": "",
  "lat": 49.6743,
  "lon": -1.6478,
  "car": null,
  "periode": null,
  "portee": null,
  "hauteur": "9.4",
  "couleur": null,
  "groupe": null,
  "type": null,
  "wikipedia": null
 },
 {
  "cible": "ouistreham",
  "osm": "node/1543873262",
  "nom": "",
  "lat": 49.2796,
  "lon": -0.2473,
  "car": "Oc",
  "periode": "12",
  "portee": "17",
  "hauteur": null,
  "couleur": "red",
  "groupe": "3+1",
  "type": "light_minor",
  "wikipedia": null
 },
 {
  "cible": "ouistreham",
  "osm": "node/1543873387",
  "nom": "",
  "lat": 49.2799,
  "lon": -0.2479,
  "car": "Oc",
  "periode": "4",
  "portee": "13",
  "hauteur": null,
  "couleur": "red",
  "groupe": null,
  "type": "light_minor",
  "wikipedia": null
 },
 {
  "cible": "ouistreham",
  "osm": "node/8401892878",
  "nom": "",
  "lat": 49.2851,
  "lon": -0.2466,
  "car": "Oc",
  "periode": "12",
  "portee": "17",
  "hauteur": null,
  "couleur": "red",
  "groupe": "3+1",
  "type": "light_minor",
  "wikipedia": null
 },
 {
  "cible": "ouistreham",
  "osm": "way/107457075",
  "nom": "Phare de Ouistreham",
  "lat": 49.2799,
  "lon": -0.2479,
  "car": null,
  "periode": null,
  "portee": null,
  "hauteur": "38",
  "couleur": null,
  "groupe": null,
  "type": null,
  "wikipedia": "fr:Phare de Ouistreham"
 },
 {
  "cible": "ver-sur-mer",
  "osm": "way/218717515",
  "nom": "Phare de Ver-sur-Mer",
  "lat": 49.3401,
  "lon": -0.5189,
  "car": "Fl",
  "periode": "15",
  "portee": "26",
  "hauteur": "42",
  "couleur": "white",
  "groupe": "3",
  "type": "landmark",
  "wikipedia": null
 }
]